<?xml version="1.0"?>

<grid name="grid5000">
	<cluster domain=".lille.grid5000.fr">
		<host name="node-1" num_procs="1"/>
		<host name="node-2" num_procs="1"/>
		<host name="node-3" num_procs="1"/>
	</cluster>
	<cluster domain=".orsay.grid5000.fr">
		<host name="node-1" num_procs="1"/>
		<host name="node-2" num_procs="1"/>
		<host name="node-3" num_procs="1"/>
	</cluster>
	<cluster domain=".sophia.grid5000.fr">
		<host name="node-1" num_procs="1"/>
		<host name="node-2" num_procs="1"/>
		<host name="node-3" num_procs="1"/>
	</cluster>
</grid>
